alpaka_job_coverage/__init__.py
alpaka_job_coverage/filter_backend_version.py
alpaka_job_coverage/filter_compiler_name.py
alpaka_job_coverage/filter_compiler_version.py
alpaka_job_coverage/filter_software_dependency.py
alpaka_job_coverage/globals.py
alpaka_job_coverage/main_functions.py
alpaka_job_coverage/util.py
alpaka_job_coverage/validate.py
alpaka_job_coverage/versions.py
alpaka_job_coverage-1.6.0.dist-info/LICENSE
alpaka_job_coverage-1.6.0.dist-info/METADATA
alpaka_job_coverage-1.6.0.dist-info/WHEEL
alpaka_job_coverage-1.6.0.dist-info/entry_points.txt
alpaka_job_coverage-1.6.0.dist-info/top_level.txt
alpaka_job_coverage-1.6.0.dist-info/RECORD
