Metadata-Version: 2.1
Name: alpaka-job-coverage
Version: 1.6.0
Summary: The library provides everything needed to generate a sparse combination matrix for alpaca-based projects, including a set of general-purpose combination rules.
Home-page: https://github.com/alpaka-group/alpaka-job-matrix-library
Author: Simeon Ehrig
Author-email: s.ehrig@hzdr.de
Project-URL: Bug Tracker, https://github.com/alpaka-group/alpaka-job-matrix-library/issues
Classifier: Programming Language :: Python :: 3
Classifier: License :: OSI Approved :: Mozilla Public License 2.0 (MPL 2.0)
Classifier: Operating System :: OS Independent
Requires-Python: >=3.8
License-File: LICENSE
Requires-Dist: allpairspy ==2.5.0
Requires-Dist: typeguard
Requires-Dist: pyaml
Requires-Dist: types-PyYAML
Requires-Dist: packaging
